wemportal/__init__.py
wemportal/constants.py
wemportal/exceptions.py
wemportal/wem_portal.py
wemportal/wem_portal_api.py
wemportal/wem_portal_web.py
wemportal/model/__init__.py
wemportal/model/wem_device.py
wemportal/model/wem_module.py
wemportal/model/wem_parameter.py
wemportal/model/wem_statistic.py
wemportal/model/wem_value.py
wemportal-0.0.5.dist-info/METADATA
wemportal-0.0.5.dist-info/WHEEL
wemportal-0.0.5.dist-info/licenses/LICENSE
wemportal-0.0.5.dist-info/RECORD
