Metadata-Version: 2.3
Name: wemportal
Version: 0.0.5
Summary: Python module for fetching wemportal data.
Project-URL: Homepage, https://github.com/floek/wemportal
Project-URL: Bug Tracker, https://github.com/floek/wemportal/issues/
Author-email: floek <root@floek.net>
License-File: LICENSE
Classifier: License :: OSI Approved :: MIT License
Classifier: Operating System :: OS Independent
Classifier: Programming Language :: Python :: 3
Requires-Python: >=3.8
Requires-Dist: beautifulsoup4>=4.11.2
Requires-Dist: python-dateutil>=2.8.2
Requires-Dist: requests>=2.28.2
